llm_cli/__init__.py
llm_cli/__init__.pyi
llm_cli/assets/__init__.py
llm_cli/assets/__init__.pyi
llm_cli/assets/prompts/__init__.py
llm_cli/assets/prompts/__init__.pyi
llm_cli/assets/prompts/commit.md
llm_cli/assets/prompts/description.md
llm_cli/assets/prompts/topics.md
llm_cli/cmd/__init__.py
llm_cli/cmd/__init__.pyi
llm_cli/cmd/_app.py
llm_cli/cmd/commit/__init__.py
llm_cli/cmd/commit/__init__.pyi
llm_cli/cmd/commit/_app.py
llm_cli/cmd/commit/_main.py
llm_cli/cmd/repo/__init__.py
llm_cli/cmd/repo/__init__.pyi
llm_cli/cmd/repo/_app.py
llm_cli/cmd/repo/_main.py
llm_cli/cmd/repo/description/__init__.py
llm_cli/cmd/repo/description/__init__.pyi
llm_cli/cmd/repo/description/_app.py
llm_cli/cmd/repo/description/_main.py
llm_cli/cmd/repo/topics/__init__.py
llm_cli/cmd/repo/topics/__init__.pyi
llm_cli/cmd/repo/topics/_app.py
llm_cli/cmd/repo/topics/_main.py
llm_cli/config/__init__.py
llm_cli/config/__init__.pyi
llm_cli/config/_config.py
llm_cli/config/_get_config.py
llm_cli/config/_init_litellm.py
llm_cli/config/_router_config.py
llm_cli/interactive/__init__.py
llm_cli/interactive/__init__.pyi
llm_cli/interactive/_output.py
llm_cli/interactive/_usage.py
llm_cli/logging/__init__.py
llm_cli/logging/__init__.pyi
llm_cli/logging/_init.py
llm_cli/logging/_loguru.py
llm_cli/utils/__init__.py
llm_cli/utils/__init__.pyi
llm_cli/utils/_add_command.py
llm_cli/utils/_as_list.py
llm_cli/utils/_extract_between_tags.py
llm_cli/utils/_get_app_dir.py
llm_cli/utils/_get_prompt.py
llm_cli/utils/_ignore.py
llm_cli/utils/_repomix.py
llm_cli/utils/_run.py
llm_cli/utils/_working_dir.py
llm_cli/utils/git/__init__.py
llm_cli/utils/git/__init__.pyi
llm_cli/utils/git/_root.py
liblaf_llm_cli-0.0.0.dist-info/METADATA
liblaf_llm_cli-0.0.0.dist-info/WHEEL
liblaf_llm_cli-0.0.0.dist-info/entry_points.txt
liblaf_llm_cli-0.0.0.dist-info/licenses/LICENSE
liblaf_llm_cli-0.0.0.dist-info/RECORD
