Metadata-Version: 2.3
Name: liblaf-llm-cli
Version: 0.0.0
Summary: 🚀 LLM CLI - a powerful, open-source command-line interface for AI-driven repository management. Simplifies commit message generation, repository description, and topic suggestion, enhancing productivity and collaboration for developers.
Author-email: liblaf <30631553+liblaf@users.noreply.github.com>
Requires-Python: >=3.12
Requires-Dist: gitpython>=3.1.43
Requires-Dist: hishel>=0.1.1
Requires-Dist: httpx[socks]>=0.27.2
Requires-Dist: lazy-loader>=0.4
Requires-Dist: litellm>=1.52.12
Requires-Dist: loguru>=0.7.2
Requires-Dist: pydantic-settings>=2.6.1
Requires-Dist: pydantic>=2.10.1
Requires-Dist: python-dotenv>=1.0.1
Requires-Dist: rich>=13.9.4
Requires-Dist: transformers>=4.46.3
Requires-Dist: typer>=0.13.1
